django_storybook/__init__.py
django_storybook/urls.py
django_storybook/views.py
django_storybook-0.1.4.dist-info/LICENSE
django_storybook-0.1.4.dist-info/METADATA
django_storybook-0.1.4.dist-info/WHEEL
django_storybook-0.1.4.dist-info/top_level.txt
django_storybook-0.1.4.dist-info/RECORD
