Metadata-Version: 2.1
Name: django-storybook
Version: 0.1.4
Summary: A Django module integrating Storybook pattern library and Django
Home-page: https://github.com/William-Blackie/django_storybook
Author: William Blackie
Author-email: contact@williamblackie.com
License: MIT
Download-URL: https://github.com/William-Blackie/django_storybook/archive/v_0.1.4.tar.gz
Keywords: Django,Pattern-library,Storybook,Pattern library
Platform: UNKNOWN
Classifier: Development Status :: 3 - Alpha
Classifier: Intended Audience :: Developers
Classifier: Topic :: Software Development
Classifier: License :: OSI Approved :: MIT License
Classifier: Programming Language :: Python :: 3.6
Requires-Python: >=3.6
